<?xml version="1.0" encoding="utf-8"?>
<LanguageData>
    <KokuV1SleepLessSkullImplant.label>V1 søvnløst hodeskalleimplantat</KokuV1SleepLessSkullImplant.label>
    <KokuV1SleepLessSkullImplant.description>En liten enhet som gjør sitt beste for å forbedre brukernes evner.</KokuV1SleepLessSkullImplant.description>
    <KokuV2SleepLessSkullImplant.label>V2 søvnløst hodeskalleimplantat</KokuV2SleepLessSkullImplant.label>
    <KokuV2SleepLessSkullImplant.description>En liten enhet som gjør sitt beste for å forbedre brukernes evner.</KokuV2SleepLessSkullImplant.description>
    <KokuV3SleepLessSkullImplant.label>V3 søvnløs hodeskalleimplantat</KokuV3SleepLessSkullImplant.label>
    <KokuV3SleepLessSkullImplant.description>En liten enhet som gjør sitt beste for å forbedre brukernes evner.</KokuV3SleepLessSkullImplant.description>
    <KokuV1PsychicLessSkullImplant.label>V1 psykisk fritt hodeskalleimplantat</KokuV1PsychicLessSkullImplant.label>
    <KokuV1PsychicLessSkullImplant.description>En liten enhet som gjør sitt beste for å forbedre brukernes evner.</KokuV1PsychicLessSkullImplant.description>
    <KokuV2PsychicLessSkullImplant.label>V2 psykisk fritt hodeskalleimplantat</KokuV2PsychicLessSkullImplant.label>
    <KokuV2PsychicLessSkullImplant.description>En liten enhet som gjør sitt beste for å forbedre brukernes evner.</KokuV2PsychicLessSkullImplant.description>
    <KokuV3PsychicLessSkullImplant.label>V3 psykisk fritt hodeskalleimplantat</KokuV3PsychicLessSkullImplant.label>
    <KokuV3PsychicLessSkullImplant.description>En liten enhet som gjør sitt beste for å forbedre brukernes evner.</KokuV3PsychicLessSkullImplant.description>
    <KokuV1ResearcherSkullImplant.label>V1-forsker Skull Implant</KokuV1ResearcherSkullImplant.label>
    <KokuV1ResearcherSkullImplant.description>En liten enhet som gjør sitt beste for å forbedre brukernes evner.</KokuV1ResearcherSkullImplant.description>
    <KokuV2ResearcherSkullImplant.label>V2-forsker Skull Implant</KokuV2ResearcherSkullImplant.label>
    <KokuV2ResearcherSkullImplant.description>En liten enhet som gjør sitt beste for å forbedre brukernes evner.</KokuV2ResearcherSkullImplant.description>
    <KokuV3ResearcherSkullImplant.label>V3-forsker Skull Implant</KokuV3ResearcherSkullImplant.label>
    <KokuV3ResearcherSkullImplant.description>En liten enhet som gjør sitt beste for å forbedre brukernes evner.</KokuV3ResearcherSkullImplant.description>
    <KokuV1MinerSkullImplant.label>V1 gruvearbeider Skull Implant</KokuV1MinerSkullImplant.label>
    <KokuV1MinerSkullImplant.description>En liten enhet som gjør sitt beste for å forbedre brukernes evner.</KokuV1MinerSkullImplant.description>
    <KokuV2MinerSkullImplant.label>V2 gruvearbeider Skull Implant</KokuV2MinerSkullImplant.label>
    <KokuV2MinerSkullImplant.description>En liten enhet som gjør sitt beste for å forbedre brukernes evner.</KokuV2MinerSkullImplant.description>
    <KokuV3MinerSkullImplant.label>V3 gruvearbeider Skull Implant</KokuV3MinerSkullImplant.label>
    <KokuV3MinerSkullImplant.description>En liten enhet som gjør sitt beste for å forbedre brukernes evner.</KokuV3MinerSkullImplant.description>
    <KokuV1FarmerSkullImplant.label>V1 farmer Skull Implant</KokuV1FarmerSkullImplant.label>
    <KokuV1FarmerSkullImplant.description>En liten enhet som gjør sitt beste for å forbedre brukernes evner.</KokuV1FarmerSkullImplant.description>
    <KokuV2FarmerSkullImplant.label>V2 farmer Skull Implant</KokuV2FarmerSkullImplant.label>
    <KokuV2FarmerSkullImplant.description>En liten enhet som gjør sitt beste for å forbedre brukernes evner.</KokuV2FarmerSkullImplant.description>
    <KokuV3FarmerSkullImplant.label>V3 farmer Skull Implant</KokuV3FarmerSkullImplant.label>
    <KokuV3FarmerSkullImplant.description>En liten enhet som gjør sitt beste for å forbedre brukernes evner.</KokuV3FarmerSkullImplant.description>
    <KokuV1RancherSkullImplant.label>V1 rancher hodeskalleimplantat</KokuV1RancherSkullImplant.label>
    <KokuV1RancherSkullImplant.description>En liten enhet som gjør sitt beste for å forbedre brukernes evner.</KokuV1RancherSkullImplant.description>
    <KokuV2RancherSkullImplant.label>V2 rancher hodeskalleimplantat</KokuV2RancherSkullImplant.label>
    <KokuV2RancherSkullImplant.description>En liten enhet som gjør sitt beste for å forbedre brukernes evner.</KokuV2RancherSkullImplant.description>
    <KokuV3RancherSkullImplant.label>V3 rancher hodeskalleimplantat</KokuV3RancherSkullImplant.label>
    <KokuV3RancherSkullImplant.description>En liten enhet som gjør sitt beste for å forbedre brukernes evner.</KokuV3RancherSkullImplant.description>
    <KokuV1ChefSkullImplant.label>V1 kokk Skull Implant</KokuV1ChefSkullImplant.label>
    <KokuV1ChefSkullImplant.description>En liten enhet som gjør sitt beste for å forbedre brukernes evner.</KokuV1ChefSkullImplant.description>
    <KokuV2ChefSkullImplant.label>V2 kokk Skull Implant</KokuV2ChefSkullImplant.label>
    <KokuV2ChefSkullImplant.description>En liten enhet som gjør sitt beste for å forbedre brukernes evner.</KokuV2ChefSkullImplant.description>
    <KokuV3ChefSkullImplant.label>V3 kokk Skull Implant</KokuV3ChefSkullImplant.label>
    <KokuV3ChefSkullImplant.description>En liten enhet som gjør sitt beste for å forbedre brukernes evner.</KokuV3ChefSkullImplant.description>
    <KokuV1BuilderSkullImplant.label>V1-bygger Skull Implant</KokuV1BuilderSkullImplant.label>
    <KokuV1BuilderSkullImplant.description>En liten enhet som gjør sitt beste for å forbedre brukernes evner.</KokuV1BuilderSkullImplant.description>
    <KokuV2BuilderSkullImplant.label>V2-bygger Skull Implant</KokuV2BuilderSkullImplant.label>
    <KokuV2BuilderSkullImplant.description>En liten enhet som gjør sitt beste for å forbedre brukernes evner.</KokuV2BuilderSkullImplant.description>
    <KokuV3BuilderSkullImplant.label>V3-bygger Skull Implant</KokuV3BuilderSkullImplant.label>
    <KokuV3BuilderSkullImplant.description>En liten enhet som gjør sitt beste for å forbedre brukernes evner.</KokuV3BuilderSkullImplant.description>
    <KokuV1MaidSkullImplant.label>V1 hushjelp Skull Implant</KokuV1MaidSkullImplant.label>
    <KokuV1MaidSkullImplant.description>En liten enhet som gjør sitt beste for å forbedre brukernes evner.</KokuV1MaidSkullImplant.description>
    <KokuV2MaidSkullImplant.label>V2 hushjelp Skull Implant</KokuV2MaidSkullImplant.label>
    <KokuV2MaidSkullImplant.description>En liten enhet som gjør sitt beste for å forbedre brukernes evner.</KokuV2MaidSkullImplant.description>
    <KokuV3MaidSkullImplant.label>V3 hushjelp Skull Implant</KokuV3MaidSkullImplant.label>
    <KokuV3MaidSkullImplant.description>En liten enhet som gjør sitt beste for å forbedre brukernes evner.</KokuV3MaidSkullImplant.description>
    <KokuV1SocialSkullImplant.label>V1 sosialt skalleimplantat</KokuV1SocialSkullImplant.label>
    <KokuV1SocialSkullImplant.description>En liten enhet som gjør sitt beste for å forbedre brukernes evner.</KokuV1SocialSkullImplant.description>
    <KokuV2SocialSkullImplant.label>V2 sosialt skalleimplantat</KokuV2SocialSkullImplant.label>
    <KokuV2SocialSkullImplant.description>En liten enhet som gjør sitt beste for å forbedre brukernes evner.</KokuV2SocialSkullImplant.description>
    <KokuV3SocialSkullImplant.label>V3 sosialt skalleimplantat</KokuV3SocialSkullImplant.label>
    <KokuV3SocialSkullImplant.description>En liten enhet som gjør sitt beste for å forbedre brukernes evner.</KokuV3SocialSkullImplant.description>
    <KokuV1MedicSkullImplant.label>V1 medic hodeskalleimplantat</KokuV1MedicSkullImplant.label>
    <KokuV1MedicSkullImplant.description>En liten enhet som gjør sitt beste for å forbedre brukernes evner.</KokuV1MedicSkullImplant.description>
    <KokuV2MedicSkullImplant.label>V2 medic hodeskalleimplantat</KokuV2MedicSkullImplant.label>
    <KokuV2MedicSkullImplant.description>En liten enhet som gjør sitt beste for å forbedre brukernes evner.</KokuV2MedicSkullImplant.description>
    <KokuV3MedicSkullImplant.label>V3 medic hodeskalleimplantat</KokuV3MedicSkullImplant.label>
    <KokuV3MedicSkullImplant.description>En liten enhet som gjør sitt beste for å forbedre brukernes evner.</KokuV3MedicSkullImplant.description>
    <KokuV1FastLearnerSkullImplant.label>V1 raskt lærende skalleimplantat</KokuV1FastLearnerSkullImplant.label>
    <KokuV1FastLearnerSkullImplant.description>En liten enhet som gjør sitt beste for å forbedre brukernes evner.</KokuV1FastLearnerSkullImplant.description>
    <KokuV2FastLearnerSkullImplant.label>V2 raskt lærende skalleimplantat</KokuV2FastLearnerSkullImplant.label>
    <KokuV2FastLearnerSkullImplant.description>En liten enhet som gjør sitt beste for å forbedre brukernes evner.</KokuV2FastLearnerSkullImplant.description>
    <KokuV3FastLearnerSkullImplant.label>V3 raskt lærende hodeskalleimplantat</KokuV3FastLearnerSkullImplant.label>
    <KokuV3FastLearnerSkullImplant.description>En liten enhet som gjør sitt beste for å forbedre brukernes evner.</KokuV3FastLearnerSkullImplant.description>
    <KokuV1MeleeSoldierSkullImplant.label>V1 nærkampssoldat Skull Implant</KokuV1MeleeSoldierSkullImplant.label>
    <KokuV1MeleeSoldierSkullImplant.description>En liten enhet som gjør sitt beste for å forbedre brukernes evner.</KokuV1MeleeSoldierSkullImplant.description>
    <KokuV2MeleeSoldierSkullImplant.label>V2 nærkampssoldat Skull Implant</KokuV2MeleeSoldierSkullImplant.label>
    <KokuV2MeleeSoldierSkullImplant.description>En liten enhet som gjør sitt beste for å forbedre brukernes evner.</KokuV2MeleeSoldierSkullImplant.description>
    <KokuV3MeleeSoldierSkullImplant.label>V3 nærkampssoldat Skull Implant</KokuV3MeleeSoldierSkullImplant.label>
    <KokuV3MeleeSoldierSkullImplant.description>En liten enhet som gjør sitt beste for å forbedre brukernes evner.</KokuV3MeleeSoldierSkullImplant.description>
    <KokuV1RangeSoldierSkullImplant.label>V1-serien soldat Skull Implant</KokuV1RangeSoldierSkullImplant.label>
    <KokuV1RangeSoldierSkullImplant.description>En liten enhet som gjør sitt beste for å forbedre brukernes evner.</KokuV1RangeSoldierSkullImplant.description>
    <KokuV2RangeSoldierSkullImplant.label>V2-serien soldat Skull Implant</KokuV2RangeSoldierSkullImplant.label>
    <KokuV2RangeSoldierSkullImplant.description>En liten enhet som gjør sitt beste for å forbedre brukernes evner.</KokuV2RangeSoldierSkullImplant.description>
    <KokuV3RangeSoldierSkullImplant.label>V3-serien soldat Skull Implant</KokuV3RangeSoldierSkullImplant.label>
    <KokuV3RangeSoldierSkullImplant.description>En liten enhet som gjør sitt beste for å forbedre brukernes evner.</KokuV3RangeSoldierSkullImplant.description>
</LanguageData>